[
  {
    "id": 1,
    "listingStatus": "approved",
    "ownerName": "mayur",
    "ownerAge": "32",
    "ownerMobile": "+91 98765 43210",
    "ownerAddress": "Baner, Pune",
    "name": "Skyline Luxury Stay",
    "location": "Viman Nagar, Pune",
    "rent": 12000,
    "gender": "Boys",
    "vacantBeds": 80,
    "totalRooms": 52,
    "wifi": true,
    "food": false,
    "laundry": false,
    "ac": true,
    "image": "https://images.unsplash.com/photo-1522771739844-6a9f6d5f14af?w=500",
    "isVerified": true
  },
  {
    "id": 1770060932772,
    "ownerName": "x",
    "ownerAge": "22",
    "ownerMobile": "s",
    "ownerAddress": "",
    "name": "s",
    "location": "s",
    "vacantBeds": 40,
    "totalRooms": 52,
    "listingStatus": "approved",
    "wifi": false,
    "food": false,
    "laundry": false,
    "ac": false,
    "image": "https://images.unsplash.com/photo-1522771739844-6a9f6d5f14af?w=500",
    "isVerified": true
  },
  {
    "id": 1770061285625,
    "ownerName": "s",
    "ownerMobile": "4",
    "listingStatus": "approved",
    "isVerified": true
  },
  {
    "id": 1770061337757,
    "ownerName": " borane",
    "ownerAge": "11",
    "ownerMobile": "2",
    "ownerAddress": "",
    "name": "sss",
    "vacantBeds": 20,
    "totalRooms": 52,
    "gender": "Boys",
    "rent": 2000,
    "sharing": [
      2,
      3
    ],
    "listingStatus": "approved",
    "wifi": false,
    "food": false,
    "laundry": false,
    "ac": false,
    "image": "https://images.unsplash.com/photo-1522771739844-6a9f6d5f14af?w=500",
    "isVerified": true
  },
  {
    "id": 1770101406039,
    "ownerName": " borane",
    "ownerAge": "112",
    "ownerMobile": "123",
    "ownerAddress": "",
    "name": "rdfghjk",
    "gender": "Boys",
    "rent": 20000,
    "vacantBeds": 25,
    "totalRooms": 52,
    "wifi": true,
    "food": true,
    "laundry": true,
    "ac": true,
    "listingStatus": "approved",
    "image": "https://images.unsplash.com/photo-1522771739844-6a9f6d5f14af?w=500",
    "isVerified": true
  }
]